mercs/__init__.py
mercs/algo/__init__.py
mercs/algo/evaluation.py
mercs/algo/imputation.py
mercs/algo/induction.py
mercs/algo/inference.py
mercs/algo/inference_v3.py
mercs/algo/new_inference.py
mercs/algo/new_prediction.py
mercs/algo/prediction.py
mercs/algo/selection.py
mercs/algo/vector_prediction.py
mercs/composition/CanonicalModel.py
mercs/composition/CompositeModel.py
mercs/composition/NewCompositeModel.py
mercs/composition/__init__.py
mercs/composition/compose.py
mercs/core/Mercs.py
mercs/core/__init__.py
mercs/graph/__init__.py
mercs/graph/graphviz.py
mercs/graph/network.py
mercs/graph/q_diagram.py
mercs/tests/__init__.py
mercs/tests/setup.py
mercs/utils/__init__.py
mercs/utils/data_handling.py
mercs/utils/debug.py
mercs/utils/decoration.py
mercs/utils/encoding.py
mercs/utils/inference_tools.py
mercs/visuals/__init__.py
mercs/visuals/diagrams.py
mercs-0.0.50.dist-info/AUTHORS.rst
mercs-0.0.50.dist-info/LICENSE.txt
mercs-0.0.50.dist-info/METADATA
mercs-0.0.50.dist-info/WHEEL
mercs-0.0.50.dist-info/top_level.txt
mercs-0.0.50.dist-info/RECORD
