Metadata-Version: 2.1
Name: mercs
Version: 0.0.50
Summary: MERCS: Multi-Directional Ensembles of Regression and Classification treeS
Home-page: https://github.com/eliavw
Author: Elia vw
Author-email: elia.vw@gmail.com
License: mit
Project-URL: Documentation, https://github.com/eliavw
Platform: any
Classifier: Development Status :: 4 - Beta
Classifier: Programming Language :: Python
Requires-Python: >=3.6
Requires-Dist: numpy
Requires-Dist: scipy
Requires-Dist: pandas
Requires-Dist: networkx
Requires-Dist: scikit-learn
Requires-Dist: dask
Requires-Dist: toolz
Requires-Dist: tornado
Requires-Dist: pydot
Requires-Dist: ipython
Provides-Extra: testing
Requires-Dist: pytest ; extra == 'testing'
